djactasauth/__init__.py
djactasauth/backends.py
djactasauth/models.py
djactasauth/util.py
djactasauth/views.py
djactasauth-0.6.0.dist-info/licenses/LICENSE
djactasauth-0.6.0.dist-info/METADATA
djactasauth-0.6.0.dist-info/WHEEL
djactasauth-0.6.0.dist-info/top_level.txt
djactasauth-0.6.0.dist-info/RECORD
