Metadata-Version: 2.4
Name: djactasauth
Version: 0.6.0
Summary: Django authentication backend allowing admins to login as another user.
Author-email: Peter Zsoldos <hello@zsoldosp.eu>
Maintainer-email: Peter Zsoldos <hello@zsoldosp.eu>
Project-URL: Homepage, https://github.com/zsoldosp/django-django-act-as-auth
Project-URL: Bug Tracker, https://github.com/zsoldosp/django-django-act-as-auth/issues
Classifier: Development Status :: 4 - Beta
Classifier: Intended Audience :: Developers
Classifier: License :: OSI Approved :: BSD License
Classifier: Operating System :: OS Independent
Classifier: Natural Language :: English
Classifier: Programming Language :: Python :: 3.9
Classifier: Programming Language :: Python :: 3.10
Classifier: Programming Language :: Python :: 3.11
Classifier: Programming Language :: Python :: 3.12
Classifier: Programming Language :: Python :: 3.13
Classifier: Framework :: Django
Classifier: Framework :: Django :: 4.2
Classifier: Framework :: Django :: 5.1
Classifier: Framework :: Django :: 5.2
Requires-Python: >=3.9
License-File: LICENSE
Requires-Dist: Django<6.0,>=4.2
Dynamic: license-file
Dynamic: requires-dist
